adjutantclient/__init__.py
adjutantclient/_i18n.py
adjutantclient/client.py
adjutantclient/exc.py
adjutantclient/common/__init__.py
adjutantclient/common/base.py
adjutantclient/common/http.py
adjutantclient/osc/__init__.py
adjutantclient/osc/plugin.py
adjutantclient/osc/v1/__init__.py
adjutantclient/osc/v1/notifications.py
adjutantclient/osc/v1/quota.py
adjutantclient/osc/v1/signup.py
adjutantclient/osc/v1/status.py
adjutantclient/osc/v1/tasks.py
adjutantclient/osc/v1/tokens.py
adjutantclient/osc/v1/users.py
adjutantclient/tests/__init__.py
adjutantclient/tests/v1/__init__.py
adjutantclient/tests/v1/test_client.py
adjutantclient/v1/__init__.py
adjutantclient/v1/client.py
adjutantclient/v1/notifications.py
adjutantclient/v1/quota.py
adjutantclient/v1/roles.py
adjutantclient/v1/signup.py
adjutantclient/v1/status.py
adjutantclient/v1/tasks.py
adjutantclient/v1/tokens.py
adjutantclient/v1/users.py
python_adjutantclient-1.5.0.dist-info/licenses/AUTHORS
python_adjutantclient-1.5.0.dist-info/licenses/LICENSE
python_adjutantclient-1.5.0.dist-info/METADATA
python_adjutantclient-1.5.0.dist-info/WHEEL
python_adjutantclient-1.5.0.dist-info/entry_points.txt
python_adjutantclient-1.5.0.dist-info/pbr.json
python_adjutantclient-1.5.0.dist-info/top_level.txt
python_adjutantclient-1.5.0.dist-info/RECORD
