Metadata-Version: 2.4
Name: python-adjutantclient
Version: 1.5.0
Summary: Adjutant API Client Library
Home-page: https://github.com/openstack/python-adjutantclient
Author: Adrian Turjak
Author-email: adriant@catalyst.net.nz
Classifier: Environment :: OpenStack
Classifier: Intended Audience :: Information Technology
Classifier: Intended Audience :: System Administrators
Classifier: License :: OSI Approved :: Apache Software License
Classifier: Operating System :: POSIX :: Linux
Classifier: Programming Language :: Python
Classifier: Programming Language :: Python :: Implementation :: CPython
Classifier: Programming Language :: Python :: 3 :: Only
Classifier: Programming Language :: Python :: 3
Classifier: Programming Language :: Python :: 3.8
Classifier: Programming Language :: Python :: 3.9
Classifier: Programming Language :: Python :: 3.10
Classifier: Programming Language :: Python :: 3.11
Requires-Python: >=3.8
License-File: LICENSE
License-File: AUTHORS
Requires-Dist: pbr>=3.0.0
Requires-Dist: cliff>=2.6.0
Requires-Dist: iso8601>=0.1.11
Requires-Dist: osc-lib>=1.8.0
Requires-Dist: PrettyTable>=0.7.1
Requires-Dist: python-openstackclient>=3.11.0
Requires-Dist: oslo.i18n>=2.1.0
Requires-Dist: oslo.serialization>=1.10.0
Requires-Dist: oslo.utils>=3.20.0
Requires-Dist: keystoneauth1>=2.20.0
Requires-Dist: PyYAML>=3.10.0
Requires-Dist: requests>=2.14.2
Dynamic: author
Dynamic: author-email
Dynamic: classifier
Dynamic: description
Dynamic: home-page
Dynamic: license-file
Dynamic: requires-dist
Dynamic: requires-python
Dynamic: summary
